README.rst
setup.py
Soar.egg-info/PKG-INFO
Soar.egg-info/SOURCES.txt
Soar.egg-info/dependency_links.txt
Soar.egg-info/entry_points.txt
Soar.egg-info/requires.txt
Soar.egg-info/top_level.txt
soar/__init__.py
soar/__main__.py
soar/client.py
soar/common.py
soar/controller.py
soar/errors.py
soar/hooks.py
soar/update.py
soar/brains/__init__.py
soar/brains/blankBrain.py
soar/gui/__init__.py
soar/gui/brain.gif
soar/gui/canvas.py
soar/gui/close.gif
soar/gui/connect.gif
soar/gui/loading.gif
soar/gui/output.py
soar/gui/pause.gif
soar/gui/play.gif
soar/gui/plot_window.py
soar/gui/reload.gif
soar/gui/sim.gif
soar/gui/soar_ui.py
soar/gui/step.gif
soar/gui/stop.gif
soar/gui/world.gif
soar/robot/__init__.py
soar/robot/arcos.py
soar/robot/base.py
soar/robot/names.py
soar/robot/pioneer.py
soar/sim/__init__.py
soar/sim/geometry.py
soar/sim/world.py
soar/worlds/__init__.py
soar/worlds/bigEmptyWorld.py
soar/worlds/bigFrustrationWorld.py
soar/worlds/frustrationWorld.py
soar/worlds/gapWorldA.py
soar/worlds/gapWorldB.py
soar/worlds/gapWorldC.py
soar/worlds/gapWorldTilt.py
soar/worlds/raceWorld.py
soar/worlds/wallFinderWorld.py
soar/worlds/wallFollowerWorld.py