Metadata-Version: 1.2
Name: Soar
Version: 1.5.1
Summary: An extensible Python framework for simulating and interacting with robots
Home-page: https://github.com/arantonitis/soar
Author: Andrew Antonitis
Author-email: andrewan@mit.edu
License: LGPLv3
Platform: UNKNOWN
Classifier: License :: OSI Approved :: GNU Lesser General Public License v3 (LGPLv3)
Classifier: Development Status :: 5 - Production/Stable
Classifier: Framework :: Robot Framework
Classifier: Intended Audience :: Education
Classifier: Programming Language :: Python :: 3.3
Classifier: Programming Language :: Python :: 3.4
Classifier: Programming Language :: Python :: 3.5
Classifier: Programming Language :: Python :: 3.6
Classifier: Programming Language :: Python :: 3.7
Requires-Python: >=3.3
